pas.plugins.cauthomatic-1.1.2-py2.7-nspkg.pth
pas/plugins/authomatic/__init__.py
pas/plugins/authomatic/configure.zcml
pas/plugins/authomatic/integration.py
pas/plugins/authomatic/interfaces.py
pas/plugins/authomatic/plugin.py
pas/plugins/authomatic/profiles.zcml
pas/plugins/authomatic/setuphandlers.py
pas/plugins/authomatic/testing.py
pas/plugins/authomatic/useridentities.py
pas/plugins/authomatic/useridfactories.py
pas/plugins/authomatic/utils.py
pas/plugins/authomatic/browser/__init__.py
pas/plugins/authomatic/browser/add_plugin.pt
pas/plugins/authomatic/browser/authomatic.png
pas/plugins/authomatic/browser/authomatic.pt
pas/plugins/authomatic/browser/configure.zcml
pas/plugins/authomatic/browser/controlpanel.py
pas/plugins/authomatic/browser/view.py
pas/plugins/authomatic/browser/resources/authomatic-logo.svg
pas/plugins/authomatic/browser/resources/authomatic.css
pas/plugins/authomatic/browser/resources/authomatic.less
pas/plugins/authomatic/locales/pas.plugins.authomatic-manual.pot
pas/plugins/authomatic/locales/pas.plugins.authomatic.pot
pas/plugins/authomatic/locales/update.sh
pas/plugins/authomatic/locales/de/LC_MESSAGES/pas.plugins.authomatic.po
pas/plugins/authomatic/locales/it/LC_MESSAGES/pas.plugins.authomatic.po
pas/plugins/authomatic/profiles/base/browserlayer.xml
pas/plugins/authomatic/profiles/base/import_steps.xml
pas/plugins/authomatic/profiles/base/metadata.xml
pas/plugins/authomatic/profiles/base/paspluginsauthomatic_marker.txt
pas/plugins/authomatic/profiles/base/registry.xml
pas/plugins/authomatic/profiles/base-uninstall/browserlayer.xml
pas/plugins/authomatic/profiles/base-uninstall/controlpanel.xml
pas/plugins/authomatic/profiles/base-uninstall/import_steps.xml
pas/plugins/authomatic/profiles/base-uninstall/paspluginsauthomatic_uninstall.txt
pas/plugins/authomatic/profiles/base-uninstall/registry.xml
pas/plugins/authomatic/profiles/plone4/controlpanel.xml
pas/plugins/authomatic/profiles/plone4/metadata.xml
pas.plugins.cauthomatic-1.1.2.dist-info/METADATA
pas.plugins.cauthomatic-1.1.2.dist-info/WHEEL
pas.plugins.cauthomatic-1.1.2.dist-info/entry_points.txt
pas.plugins.cauthomatic-1.1.2.dist-info/namespace_packages.txt
pas.plugins.cauthomatic-1.1.2.dist-info/top_level.txt
pas.plugins.cauthomatic-1.1.2.dist-info/RECORD
