Metadata-Version: 2.1
Name: pas.plugins.cauthomatic
Version: 1.1.2
Summary: Provides OAuth2/ OpenID login for Plone using Authomatic.
Home-page: http://pypi.python.org/pypi/pas.plugins.authomatic
Author: Jens Klein and Matthias Dollfuss
Author-email: dev@bluedynamics.com
License: GPL
Keywords: Python Plone PAS OAuth
Platform: UNKNOWN
Classifier: Environment :: Web Environment
Classifier: Framework :: Plone
Classifier: Framework :: Plone :: 4.3
Classifier: Framework :: Plone :: 5.0
Classifier: Framework :: Plone :: 5.1
Classifier: Programming Language :: Python
Classifier: Programming Language :: Python :: 2.7
Requires-Dist: CAuthomatic
Requires-Dist: Plone
Requires-Dist: plone.api
Requires-Dist: plone.protect (>=3.0.0)
Requires-Dist: setuptools
Provides-Extra: test
Requires-Dist: mock ; extra == 'test'
Requires-Dist: plone.app.contenttypes ; extra == 'test'
Requires-Dist: plone.app.robotframework[debug] ; extra == 'test'
Requires-Dist: plone.app.testing ; extra == 'test'
